{"cameraMode":{"drawMode":0,"name":"Shaded","section":"Shading Mode"},"sceneLighting":true,"audioPlay":false,"sceneViewState":{"showFog":true,"showMaterialUpdate":false,"showSkybox":true,"showFlares":true,"showImageEffects":true,"showParticleSystems":true},"in2DMode":false,"pivot":{"x":-2.0745017528533937,"y":1.0443079471588135,"z":-0.9528342485427856},"rotation":{"x":-0.11881190538406372,"y":0.6824537515640259,"z":-0.11385524272918701,"w":-0.712164044380188},"size":4.310543060302734,"orthographic":false}